CHANGES.rst
LICENSE.txt
MANIFEST.in
README.rst
setup.cfg
setup.py
rotating_free_proxies/__init__.py
rotating_free_proxies/expire.py
rotating_free_proxies/middlewares.py
rotating_free_proxies/policy.py
rotating_free_proxies/utils.py
rotating_free_proxies.egg-info/PKG-INFO
rotating_free_proxies.egg-info/SOURCES.txt
rotating_free_proxies.egg-info/dependency_links.txt
rotating_free_proxies.egg-info/requires.txt
rotating_free_proxies.egg-info/top_level.txt