Metadata-Version: 1.1
Name: rotating-free-proxies
Version: 0.1.2
Summary: Rotating proxies for Scrapy
Home-page: https://github.com/nabinkhadka/rotating-free-proxies
Author: Nabin Khadka
Author-email: nbnkhadka14@gmail.com
License: MIT license
Platform: UNKNOWN
Classifier: Development Status :: 3 - Alpha
Classifier: License :: OSI Approved :: MIT License
Classifier: Intended Audience :: Developers
Classifier: Operating System :: OS Independent
Classifier: Framework :: Scrapy
Classifier: Programming Language :: Python
Classifier: Programming Language :: Python :: 3
Classifier: Programming Language :: Python :: 3.7
Classifier: Programming Language :: Python :: 3.8
